ambient_sdk/__init__.py
ambient_sdk/_base_client.py
ambient_sdk/_client.py
ambient_sdk/_compat.py
ambient_sdk/_constants.py
ambient_sdk/_exceptions.py
ambient_sdk/_files.py
ambient_sdk/_models.py
ambient_sdk/_qs.py
ambient_sdk/_resource.py
ambient_sdk/_response.py
ambient_sdk/_streaming.py
ambient_sdk/_types.py
ambient_sdk/_version.py
ambient_sdk/py.typed
ambient_sdk/_utils/__init__.py
ambient_sdk/_utils/_compat.py
ambient_sdk/_utils/_datetime_parse.py
ambient_sdk/_utils/_logs.py
ambient_sdk/_utils/_proxy.py
ambient_sdk/_utils/_reflection.py
ambient_sdk/_utils/_resources_proxy.py
ambient_sdk/_utils/_streams.py
ambient_sdk/_utils/_sync.py
ambient_sdk/_utils/_transform.py
ambient_sdk/_utils/_typing.py
ambient_sdk/_utils/_utils.py
ambient_sdk/lib/.keep
ambient_sdk/resources/__init__.py
ambient_sdk/resources/authorization.py
ambient_sdk/resources/employer.py
ambient_sdk/resources/health.py
ambient_sdk/resources/report.py
ambient_sdk/resources/transaction.py
ambient_sdk/resources/employee/__init__.py
ambient_sdk/resources/employee/balance.py
ambient_sdk/resources/employee/employee.py
ambient_sdk/resources/org/__init__.py
ambient_sdk/resources/org/org.py
ambient_sdk/resources/org/employee/__init__.py
ambient_sdk/resources/org/employee/employee.py
ambient_sdk/resources/org/employee/payment_methods.py
ambient_sdk/types/__init__.py
ambient_sdk/types/authorization_retrieve_response.py
ambient_sdk/types/employee_archive_params.py
ambient_sdk/types/employee_archive_response.py
ambient_sdk/types/employee_batch_create_params.py
ambient_sdk/types/employee_batch_create_response.py
ambient_sdk/types/employee_core.py
ambient_sdk/types/employee_core_param.py
ambient_sdk/types/employee_create_params.py
ambient_sdk/types/employee_create_response.py
ambient_sdk/types/employee_get_payment_methods_response.py
ambient_sdk/types/employee_get_transactions_params.py
ambient_sdk/types/employee_get_transactions_response.py
ambient_sdk/types/employee_unarchive_response.py
ambient_sdk-0.1.0a14.dist-info/METADATA
ambient_sdk-0.1.0a14.dist-info/WHEEL
ambient_sdk-0.1.0a14.dist-info/licenses/LICENSE
ambient_sdk-0.1.0a14.dist-info/RECORD
